LICENSE
MANIFEST.in
NOTICE
README.md
requirements.txt
setup.py
carbon/__init__.py
carbon/cli.py
carbon/constants.py
carbon/main.py
carbon/utils.py
carbon_api.egg-info/PKG-INFO
carbon_api.egg-info/SOURCES.txt
carbon_api.egg-info/dependency_links.txt
carbon_api.egg-info/entry_points.txt
carbon_api.egg-info/not-zip-safe
carbon_api.egg-info/requires.txt
carbon_api.egg-info/top_level.txt